image_array_and_histogram/__init__.py
image_array_and_histogram/main.py
image_array_and_histogram_rrsc-0.0.2.dist-info/LICENSE
image_array_and_histogram_rrsc-0.0.2.dist-info/METADATA
image_array_and_histogram_rrsc-0.0.2.dist-info/WHEEL
image_array_and_histogram_rrsc-0.0.2.dist-info/top_level.txt
image_array_and_histogram_rrsc-0.0.2.dist-info/RECORD
