Metadata-Version: 2.1
Name: image-array-and-histogram-rrsc
Version: 0.0.2
Summary: Helps in getting array and histogram of a greyscale image. Also, image from the array.
Home-page: https://github.com/rishi-chauhan/my-packages.git
Author: Rishi Raj Singh Chauhan
Author-email: rishirschauhan@gmail.com
License: UNKNOWN
Platform: UNKNOWN
Classifier: Programming Language :: Python :: 2.7
Classifier: License :: OSI Approved :: MIT License
Classifier: Operating System :: OS Independent
